{
  "authSelections": "userPoolOnly",
  "resourceName": "biolinkwebsitedowngrbac1149e",
  "serviceType": "imported",
  "region": "us-east-1",
  "usernameAttributes": [
    "email"
  ],
  "requiredAttributes": [
    "name",
    "email",
    "phone_number"
  ],
  "passwordPolicyMinLength": 8,
  "passwordPolicyCharacters": [
    "Requires Lowercase",
    "Requires Uppercase",
    "Requires Numbers",
    "Requires Symbols"
  ],
  "mfaConfiguration": "ON",
  "autoVerifiedAttributes": [
    "email"
  ],
  "mfaTypes": [
    "SMS Text Message"
  ]
}